simple_mockforce/__init__.py
simple_mockforce/callbacks.py
simple_mockforce/constants.py
simple_mockforce/error_codes.py
simple_mockforce/query_algorithms/__init__.py
simple_mockforce/query_algorithms/date_token.py
simple_mockforce/query_algorithms/order_by.py
simple_mockforce/query_algorithms/parent_attrs.py
simple_mockforce/query_algorithms/where.py
simple_mockforce/utils.py
simple_mockforce/virtual.py
simple_mockforce-0.8.0.dist-info/LICENSE
simple_mockforce-0.8.0.dist-info/WHEEL
simple_mockforce-0.8.0.dist-info/METADATA
simple_mockforce-0.8.0.dist-info/RECORD
