Metadata-Version: 2.1
Name: simple-mockforce
Version: 0.8.0
Summary: A companion package for simple-salesforce that enables the testing of code that interacts with Salesforce's API
Home-page: https://github.com/Kicksaw-Consulting/simple-mockforce
License: MIT
Keywords: python,simple-salesforce,salesforce,testing,mocking
Author: Alex Drozd
Author-email: drozdster@gmail.com
Requires-Python: >=3.8,<4.0
Classifier: License :: OSI Approved :: MIT License
Classifier: Programming Language :: Python :: 3
Classifier: Programming Language :: Python :: 3.8
Classifier: Programming Language :: Python :: 3.9
Classifier: Programming Language :: Python :: 3.10
Requires-Dist: decorator (>=5.1.1,<6.0.0)
Requires-Dist: python-dateutil (>=2.8.2,<3.0.0)
Requires-Dist: python-soql-parser (>=0.2.0,<0.3.0)
Requires-Dist: responses (>=0.20.0,<0.21.0)
Project-URL: Repository, https://github.com/Kicksaw-Consulting/simple-mockforce
